ndn_python_repo/__init__.py
ndn_python_repo/config.py
ndn_python_repo/ndn-python-repo.conf.sample
ndn_python_repo/ndn-python-repo.service
ndn_python_repo/repo.py
ndn_python_repo/clients/__init__.py
ndn_python_repo/clients/command_checker.py
ndn_python_repo/clients/delete.py
ndn_python_repo/clients/getfile.py
ndn_python_repo/clients/putfile.py
ndn_python_repo/cmd/__init__.py
ndn_python_repo/cmd/install.py
ndn_python_repo/cmd/main.py
ndn_python_repo/cmd/port.py
ndn_python_repo/command/__init__.py
ndn_python_repo/command/repo_commands.py
ndn_python_repo/handle/__init__.py
ndn_python_repo/handle/command_handle_base.py
ndn_python_repo/handle/delete_command_handle.py
ndn_python_repo/handle/read_handle.py
ndn_python_repo/handle/tcp_bulk_insert_handle.py
ndn_python_repo/handle/write_command_handle.py
ndn_python_repo/storage/__init__.py
ndn_python_repo/storage/leveldb.py
ndn_python_repo/storage/mongodb.py
ndn_python_repo/storage/sqlite.py
ndn_python_repo/storage/storage_base.py
ndn_python_repo/storage/storage_factory.py
ndn_python_repo/utils/__init__.py
ndn_python_repo/utils/concurrent_fetcher.py
ndn_python_repo/utils/pubsub.py
ndn_python_repo-0.3.dist-info/COPYING
ndn_python_repo-0.3.dist-info/METADATA
ndn_python_repo-0.3.dist-info/WHEEL
ndn_python_repo-0.3.dist-info/entry_points.txt
ndn_python_repo-0.3.dist-info/top_level.txt
ndn_python_repo-0.3.dist-info/RECORD
