Metadata-Version: 2.1
Name: ndn-python-repo
Version: 0.3
Summary: An NDN Repo implementation using Python
Home-page: https://github.com/UCLA-IRL/ndn-python-repo
Download-URL: https://pypi.python.org/pypi/ndn-python-repo
Author: Zhaoning Kong
Author-email: jonnykong@cs.ucla.edu
License: Apache License 2.0
Project-URL: Bug Tracker, https://github.com/UCLA-IRL/ndn-python-repo/issues
Project-URL: Source Code, https://github.com/UCLA-IRL/ndn-python-repo
Keywords: NDN
Classifier: Development Status :: 4 - Beta
Classifier: Topic :: Database
Classifier: Topic :: Internet
Classifier: Topic :: System :: Networking
Classifier: License :: OSI Approved :: Apache Software License
Classifier: Programming Language :: Python :: 3.9
Classifier: Programming Language :: Python :: 3.10
Requires-Python: >=3.9
License-File: COPYING
Requires-Dist: python-ndn (>=0.3.post1)
Requires-Dist: PyYAML (>=6.0)
Provides-Extra: leveldb
Requires-Dist: plyvel ; extra == 'leveldb'
Provides-Extra: mongodb
Requires-Dist: pymongo ; extra == 'mongodb'
Provides-Extra: test
Requires-Dist: pytest ; extra == 'test'
Requires-Dist: pytest-cov ; extra == 'test'
